sphinx_linkfix/__init__.py
sphinx_linkfix/_version.py
sphinx_linkfix/_version.pyi
sphinx_linkfix/extension.py
sphinx_linkfix-0.2.0.dist-info/licenses/AUTHORS.rst
sphinx_linkfix-0.2.0.dist-info/licenses/LICENSE.txt
sphinx_linkfix-0.2.0.dist-info/METADATA
sphinx_linkfix-0.2.0.dist-info/WHEEL
sphinx_linkfix-0.2.0.dist-info/top_level.txt
sphinx_linkfix-0.2.0.dist-info/RECORD
