Metadata-Version: 2.4
Name: sphinx-linkfix
Version: 0.2.0
Summary: Sphinx extension that rewrites GitHub-style links into proper Sphinx references.
Author-email: Javier Moralejo Piñas <j.moralejo.pinas@gmail.com>
License: MIT
Project-URL: Homepage, https://github.com/j-moralejo-pinas/sphinx-linkfix
Project-URL: Changelog, https://sphinx-linkfix.readthedocs.io/en/latest/CHANGELOG.html
Project-URL: Source, https://github.com/j-moralejo-pinas/sphinx-linkfix
Project-URL: Documentation, https://sphinx-linkfix.readthedocs.io/
Project-URL: Tracker, https://github.com/j-moralejo-pinas/sphinx-linkfix/issues
Keywords: sphinx,sphinx-extension,github,links,references
Classifier: Programming Language :: Python :: 3
Classifier: License :: OSI Approved :: MIT License
Classifier: Operating System :: OS Independent
Classifier: Intended Audience :: Developers
Classifier: Environment :: Plugins
Classifier: Topic :: Documentation
Classifier: Topic :: Documentation :: Sphinx
Classifier: Topic :: Software Development :: Documentation
Classifier: Topic :: Software Development :: Build Tools
Classifier: Topic :: Text Processing :: Markup
Classifier: Topic :: Text Processing :: Markup :: reStructuredText
Classifier: Framework :: Sphinx
Classifier: Framework :: Sphinx :: Extension
Requires-Python: >=3.9
License-File: LICENSE.txt
License-File: AUTHORS.rst
Requires-Dist: sphinx
Requires-Dist: docutils
Provides-Extra: dev
Requires-Dist: pytest; extra == "dev"
Requires-Dist: pyright; extra == "dev"
Requires-Dist: pre-commit; extra == "dev"
Requires-Dist: ruff; extra == "dev"
Requires-Dist: pydoclint; extra == "dev"
Requires-Dist: docformatter; extra == "dev"
Requires-Dist: pytest; extra == "dev"
Requires-Dist: pytest-cov; extra == "dev"
Requires-Dist: pyupgrade; extra == "dev"
Requires-Dist: twine; extra == "dev"
Requires-Dist: build; extra == "dev"
Provides-Extra: docs
Requires-Dist: sphinx; extra == "docs"
Requires-Dist: sphinx-autoapi; extra == "docs"
Requires-Dist: sphinx-rtd-theme; extra == "docs"
Requires-Dist: sphinx-linkfix; extra == "docs"
Provides-Extra: format
Requires-Dist: ruff; extra == "format"
Requires-Dist: docformatter; extra == "format"
Requires-Dist: pyupgrade; extra == "format"
Provides-Extra: code-quality
Requires-Dist: ruff; extra == "code-quality"
Requires-Dist: pydoclint; extra == "code-quality"
Requires-Dist: pyright; extra == "code-quality"
Provides-Extra: test
Requires-Dist: pytest; extra == "test"
Requires-Dist: pytest-cov; extra == "test"
Dynamic: license-file
